ygg_keyfile/__init__.py
ygg_keyfile/keyfile.py
ygg_keyfile-0.1.0.dist-info/LICENSE
ygg_keyfile-0.1.0.dist-info/METADATA
ygg_keyfile-0.1.0.dist-info/WHEEL
ygg_keyfile-0.1.0.dist-info/top_level.txt
ygg_keyfile-0.1.0.dist-info/RECORD
