Metadata-Version: 2.1
Name: ygg-keyfile
Version: 0.1.0
Summary: A library for handling the encrypted keyfiles used to store yggdrash private keys.
Home-page: https://github.com/yggdrash/ygg-keyfile
Author: Yggdrash Dev
Author-email: dev@yggdrash.io
License: MIT
Keywords: ethereum
Platform: UNKNOWN
Classifier: Development Status :: 2 - Pre-Alpha
Classifier: Intended Audience :: Developers
Classifier: License :: OSI Approved :: MIT License
Classifier: Natural Language :: English
Classifier: Programming Language :: Python :: 2
Classifier: Programming Language :: Python :: 2.7
Classifier: Programming Language :: Python :: 3
Classifier: Programming Language :: Python :: 3.4
Classifier: Programming Language :: Python :: 3.5
Requires-Dist: eth-utils (<2,>=1.3.0)
Requires-Dist: eth-keys (<0.3.0,>=0.2.1)
Requires-Dist: pycryptodome (<4,>=3.6.6)
Provides-Extra: dev
Requires-Dist: eth-utils (<2,>=1.3.0) ; extra == 'dev'
Requires-Dist: eth-keys (<0.3.0,>=0.2.1) ; extra == 'dev'
Requires-Dist: pycryptodome (<4,>=3.6.6) ; extra == 'dev'
Requires-Dist: bumpversion (<1,>=0.5.3) ; extra == 'dev'
Requires-Dist: wheel ; extra == 'dev'
Requires-Dist: setuptools (>=36.2.0) ; extra == 'dev'
Requires-Dist: pluggy (==0.7.1) ; extra == 'dev'
Requires-Dist: idna (==2.7) ; extra == 'dev'
Requires-Dist: requests (<3,>=2.20) ; extra == 'dev'
Requires-Dist: tox (>=2.7.0) ; extra == 'dev'
Requires-Dist: twine ; extra == 'dev'
Requires-Dist: pytest (<3.7,>=3.6) ; extra == 'dev'
Requires-Dist: flake8 (==3.5.0) ; extra == 'dev'
Provides-Extra: keyfile
Requires-Dist: eth-utils (<2,>=1.3.0) ; extra == 'keyfile'
Requires-Dist: eth-keys (<0.3.0,>=0.2.1) ; extra == 'keyfile'
Requires-Dist: pycryptodome (<4,>=3.6.6) ; extra == 'keyfile'
Provides-Extra: lint
Requires-Dist: flake8 (==3.5.0) ; extra == 'lint'
Provides-Extra: test
Requires-Dist: pytest (<3.7,>=3.6) ; extra == 'test'
